great_expectations_experimental/__init__.py
great_expectations_experimental/expectations/__init__.py
great_expectations_experimental/expectations/expect_column_chisquare_simple_test_p_value_to_be_greater_than.py
great_expectations_experimental/expectations/expect_column_discrete_entropy_to_be_between.py
great_expectations_experimental/expectations/expect_column_distinct_values_to_be_continuous.py
great_expectations_experimental/expectations/expect_column_distribution_to_match_benfords_law.py
great_expectations_experimental/expectations/expect_column_kolmogoro_smirnov_test_p_value_to_be_greater_than.py
great_expectations_experimental/expectations/expect_column_kurtosis_to_be_between.py
great_expectations_experimental/expectations/expect_column_pair_values_to_have_difference_of_custom_percentage.py
great_expectations_experimental/expectations/expect_column_percentile_value_to_be_above.py
great_expectations_experimental/expectations/expect_column_skew_to_be_between.py
great_expectations_experimental/expectations/expect_column_sum_to_be.py
great_expectations_experimental/expectations/expect_column_to_have_no_days_missing.py
great_expectations_experimental/expectations/expect_column_to_have_no_months_missing.py
great_expectations_experimental/expectations/expect_column_values_after_split_to_be_in_set.py
great_expectations_experimental/expectations/expect_column_values_after_split_to_be_unique.py
great_expectations_experimental/expectations/expect_column_values_not_to_be_future_date.py
great_expectations_experimental/expectations/expect_column_values_number_of_decimal_places_to_equal.py
great_expectations_experimental/expectations/expect_column_values_to_be_alphabetical.py
great_expectations_experimental/expectations/expect_column_values_to_be_edtf_parseable.py
great_expectations_experimental/expectations/expect_column_values_to_be_hexadecimal.py
great_expectations_experimental/expectations/expect_column_values_to_be_in_set_spark_optimized.py
great_expectations_experimental-0.1.20240917055.dist-info/METADATA
great_expectations_experimental-0.1.20240917055.dist-info/WHEEL
great_expectations_experimental-0.1.20240917055.dist-info/top_level.txt
great_expectations_experimental-0.1.20240917055.dist-info/RECORD
