Metadata-Version: 2.1
Name: great-expectations-experimental
Version: 0.1.20240917055
Summary: Always know what to expect from your data.
Home-page: https://github.com/great-expectations/great_expectations
Author: The Great Expectations Team
Author-email: team@greatexpectations.io
License: Apache-2.0
Keywords: data science testing pipeline data quality dataquality validation datavalidation
Platform: UNKNOWN
Classifier: Development Status :: 4 - Beta
Classifier: Intended Audience :: Developers
Classifier: Intended Audience :: Science/Research
Classifier: Intended Audience :: Other Audience
Classifier: Topic :: Scientific/Engineering
Classifier: Topic :: Software Development
Classifier: Topic :: Software Development :: Testing
Classifier: License :: OSI Approved :: Apache Software License
Classifier: Programming Language :: Python :: 3
Classifier: Programming Language :: Python :: 3.7
Classifier: Programming Language :: Python :: 3.8
Classifier: Programming Language :: Python :: 3.9
Requires-Dist: great-expectations>=0.13.0
